odoo/addons/sale_quick/README.rst
odoo/addons/sale_quick/__init__.py
odoo/addons/sale_quick/__manifest__.py
odoo/addons/sale_quick/i18n/fr.po
odoo/addons/sale_quick/i18n/it.po
odoo/addons/sale_quick/i18n/sale_quick.pot
odoo/addons/sale_quick/models/__init__.py
odoo/addons/sale_quick/models/product_product.py
odoo/addons/sale_quick/models/sale_order.py
odoo/addons/sale_quick/readme/CONTRIBUTORS.rst
odoo/addons/sale_quick/readme/DESCRIPTION.rst
odoo/addons/sale_quick/readme/USAGE.rst
odoo/addons/sale_quick/static/description/icon.png
odoo/addons/sale_quick/static/description/index.html
odoo/addons/sale_quick/tests/__init__.py
odoo/addons/sale_quick/tests/test_quick_sale.py
odoo/addons/sale_quick/views/product_view.xml
odoo/addons/sale_quick/views/sale_view.xml
odoo14_addon_sale_quick-14.0.1.0.4.dist-info/METADATA
odoo14_addon_sale_quick-14.0.1.0.4.dist-info/WHEEL
odoo14_addon_sale_quick-14.0.1.0.4.dist-info/top_level.txt
odoo14_addon_sale_quick-14.0.1.0.4.dist-info/RECORD
